[
    {
        "name": "some name",
        "_id": "f28kf1wkov616vm"
    },
    {
        "name": "Dan",
        "_id": "f28k9vskovktbsb"
    },
    {
        "name": "JJ",
        "_id": "f28k8awkovktg57"
    },
    {
        "_id": "f28k4k8kowx1xxt",
        "createdAt": "2021-05-20T13:14:53.584Z"
    },
    {
        "_id": "f28k494kox1elik",
        "createdAt": "2021-05-20T15:16:42.475Z"
    },
    {
        "name": "Carlos",
        "_id": "f28kbickovkt6gn",
        "img": "http://localhost:3001/img/authors/Eat228.jpg"
    },
    {
        "_id": "f28k8xkkox1hz1i",
        "createdAt": "2021-05-20T15:19:19.973Z"
    },
    {
        "name": "Mikey the madman",
        "_id": "f28k1ackowx308g",
        "modifiedAt": "2021-05-20T13:16:24.419Z",
        "img": "http://localhost:3001/img/authors/Eat228.jpg"
    }
]